aipkgs_heartbeat/__init__.py
aipkgs_heartbeat/ai_heartbeat.py
aipkgs_heartbeat-1.0.2.dist-info/LICENSE.md
aipkgs_heartbeat-1.0.2.dist-info/METADATA
aipkgs_heartbeat-1.0.2.dist-info/WHEEL
aipkgs_heartbeat-1.0.2.dist-info/RECORD
