Metadata-Version: 2.1
Name: aipkgs-heartbeat
Version: 1.0.2
Summary: A simple heartbeat service for aipy packages
Home-page: https://gitlab.com/aipy/public/packages.git
License: MIT
Keywords: ai
Author: Alexy
Author-email: alexy.ib@outlook.com
Requires-Python: >=3.11.4,<4.0.0
Classifier: License :: OSI Approved :: MIT License
Classifier: Programming Language :: Python :: 3
Classifier: Programming Language :: Python :: 3.12
Requires-Dist: APScheduler (>=3.10.4,<4.0.0)
Requires-Dist: Flask-APScheduler (>=1.13.1,<2.0.0)
Project-URL: Repository, https://gitlab.com/aipy/public/packages.git
